dell_powerstore_mcp_server-1.0.1.dist-info/licenses/LICENSE
powerstore_mcp/__init__.py
powerstore_mcp/api_client.py
powerstore_mcp/config.py
powerstore_mcp/exceptions.py
powerstore_mcp/http_server.py
powerstore_mcp/logging_config.py
powerstore_mcp/main.py
powerstore_mcp/py.typed
powerstore_mcp/server.py
powerstore_mcp/tool_generator.py
dell_powerstore_mcp_server-1.0.1.dist-info/METADATA
dell_powerstore_mcp_server-1.0.1.dist-info/WHEEL
dell_powerstore_mcp_server-1.0.1.dist-info/entry_points.txt
dell_powerstore_mcp_server-1.0.1.dist-info/top_level.txt
dell_powerstore_mcp_server-1.0.1.dist-info/RECORD
