Metadata-Version: 2.4
Name: dell-powerstore-mcp-server
Version: 1.0.1
Summary: MCP Server for Dell PowerStore with automatic OpenAPI tool generation - Credential-free mode
Author-email: sachdev27 <opensource@sachdev27.com>
Maintainer-email: sachdev27 <opensource@sachdev27.com>
License: MIT
Project-URL: Homepage, https://github.com/sachdev27/dell-powerstore-mcp-server
Project-URL: Documentation, https://github.com/sachdev27/dell-powerstore-mcp-server#readme
Project-URL: Repository, https://github.com/sachdev27/dell-powerstore-mcp-server.git
Project-URL: Issues, https://github.com/sachdev27/dell-powerstore-mcp-server/issues
Project-URL: Changelog, https://github.com/sachdev27/dell-powerstore-mcp-server/blob/main/CHANGELOG.md
Keywords: mcp,model-context-protocol,dell,powerstore,storage,openapi,ai,llm,claude,automation
Classifier: Development Status :: 4 - Beta
Classifier: Environment :: Console
Classifier: Environment :: Web Environment
Classifier: Framework :: AsyncIO
Classifier: Intended Audience :: Developers
Classifier: Intended Audience :: System Administrators
Classifier: License :: OSI Approved :: MIT License
Classifier: Operating System :: OS Independent
Classifier: Programming Language :: Python :: 3
Classifier: Programming Language :: Python :: 3.10
Classifier: Programming Language :: Python :: 3.11
Classifier: Programming Language :: Python :: 3.12
Classifier: Programming Language :: Python :: 3.13
Classifier: Topic :: System :: Systems Administration
Classifier: Topic :: Software Development :: Libraries :: Python Modules
Classifier: Typing :: Typed
Requires-Python: >=3.10
License-File: LICENSE
Requires-Dist: mcp>=1.0.0
Requires-Dist: httpx>=0.27.0
Requires-Dist: pydantic>=2.0.0
Requires-Dist: python-dotenv>=1.0.0
Requires-Dist: pyyaml>=6.0.0
Requires-Dist: starlette>=0.36.0
Requires-Dist: uvicorn[standard]>=0.27.0
Provides-Extra: dev
Requires-Dist: pytest>=8.0.0; extra == "dev"
Requires-Dist: pytest-asyncio>=0.23.0; extra == "dev"
Requires-Dist: pytest-cov>=4.1.0; extra == "dev"
Requires-Dist: pytest-mock>=3.12.0; extra == "dev"
Requires-Dist: black>=24.0.0; extra == "dev"
Requires-Dist: ruff>=0.3.0; extra == "dev"
Requires-Dist: mypy>=1.8.0; extra == "dev"
Requires-Dist: pre-commit>=3.6.0; extra == "dev"
Requires-Dist: types-PyYAML>=6.0.0; extra == "dev"
Provides-Extra: docs
Requires-Dist: mkdocs>=1.5.0; extra == "docs"
Requires-Dist: mkdocs-material>=9.5.0; extra == "docs"
Requires-Dist: mkdocstrings[python]>=0.24.0; extra == "docs"
Dynamic: license-file
